vidmerge_zoomout/__init__.py
vidmerge_zoomout/__main__.py
vidmerge_zoomout/generate_zoom_out_video.py
vidmerge_zoomout-0.2.0.dist-info/METADATA
vidmerge_zoomout-0.2.0.dist-info/WHEEL
vidmerge_zoomout-0.2.0.dist-info/top_level.txt
vidmerge_zoomout-0.2.0.dist-info/RECORD
