Metadata-Version: 2.1
Name: vidmerge_zoomout
Version: 0.2.0
Requires-Python: >=3.6
Requires-Dist: opencv-python >=4.5.1
Requires-Dist: tqdm >=4.56.0
Requires-Dist: pathlib
